napalm_nokia_olt/__init__.py
napalm_nokia_olt/nokia_olt.py
napalm_nokia_olt-0.0.51.dist-info/LICENSE.md
napalm_nokia_olt-0.0.51.dist-info/METADATA
napalm_nokia_olt-0.0.51.dist-info/WHEEL
napalm_nokia_olt-0.0.51.dist-info/top_level.txt
napalm_nokia_olt-0.0.51.dist-info/RECORD
