Metadata-Version: 2.1
Name: napalm_nokia_olt
Version: 0.0.51
Summary: Network Automation and Programmability Abstraction Layer driver for NOKIA OLT 
Home-page: https://github.com/davama/napalm-nokia_olt
Author: Dave Macias
Author-email: davama@gmail.com
Keywords: napalm driver
Classifier: Topic :: Utilities
Classifier: Programming Language :: Python :: 3
Classifier: Operating System :: OS Independent
Classifier: License :: OSI Approved :: BSD License
License-File: LICENSE.md
Requires-Dist: napalm >=3
Requires-Dist: xmltodict
